SatyrScheduler/__init__.py
SatyrScheduler/CreateSchedule/__init__.py
SatyrScheduler/DeploySchedule/__init__.py
SatyrScheduler/GetData/GetData.py
SatyrScheduler/GetData/__init__.py
SatyrScheduler/Schedule/Schedule.py
SatyrScheduler/Schedule/__init__.py
SatyrScheduler-0.0.3.dist-info/LICENSE
SatyrScheduler-0.0.3.dist-info/METADATA
SatyrScheduler-0.0.3.dist-info/WHEEL
SatyrScheduler-0.0.3.dist-info/top_level.txt
SatyrScheduler-0.0.3.dist-info/RECORD
