Metadata-Version: 2.1
Name: SatyrScheduler
Version: 0.0.3
Summary: A small package to create a schedule for Satyr
Home-page: https://github.com/nickgismokato/Satyr-scheduler
Author: nickgismokato
Author-email: nickvillumlaursen@gmail.com
License: MIT License
Keywords: python,satyr,package
Classifier: Development Status :: 2 - Pre-Alpha
Classifier: Intended Audience :: End Users/Desktop
Classifier: Intended Audience :: Other Audience
Classifier: Programming Language :: Python :: 3
Classifier: Operating System :: OS Independent
Requires-Python: >=3.10
License-File: LICENSE
